{
  "2017-06-29": {
    "open": 19.25,
    "high": 20.8,
    "low": 18.185,
    "close": 19.81,
    "volume": 2054797
  },
  "2017-06-30": {
    "open": 20.2,
    "high": 22.4,
    "low": 19.54,
    "close": 22.29,
    "volume": 426066
  },
  "2017-07-03": {
    "open": 22.7,
    "high": 23.4999,
    "low": 22.51,
    "close": 23.33,
    "volume": 195421
  },
  "2017-07-05": {
    "open": 23.52,
    "high": 23.6703,
    "low": 22.078,
    "close": 22.71,
    "volume": 143344
  },
  "2017-07-06": {
    "open": 22.74,
    "high": 23.71,
    "low": 22.01,
    "close": 23.32,
    "volume": 264343
  },
  "2017-07-07": {
    "open": 23.4,
    "high": 25.25,
    "low": 22.98,
    "close": 25.17,
    "volume": 112807
  },
  "2017-07-10": {
    "open": 24.96,
    "high": 28.59,
    "low": 24.8673,
    "close": 27.47,
    "volume": 186295
  },
  "2017-07-11": {
    "open": 27.37,
    "high": 27.82,
    "low": 25.9,
    "close": 26.81,
    "volume": 122253
  },
  "2017-07-12": {
    "open": 26.5,
    "high": 26.5,
    "low": 25.101,
    "close": 25.4,
    "volume": 126170
  },
  "2017-07-13": {
    "open": 25.61,
    "high": 26.2519,
    "low": 22.81,
    "close": 24.99,
    "volume": 161026
  },
  "2017-07-14": {
    "open": 25.0,
    "high": 25.25,
    "low": 24.0,
    "close": 24.03,
    "volume": 99901
  },
  "2017-07-17": {
    "open": 24.37,
    "high": 25.7,
    "low": 23.02,
    "close": 23.9,
    "volume": 107958
  },
  "2017-07-18": {
    "open": 24.17,
    "high": 24.75,
    "low": 23.5665,
    "close": 24.0,
    "volume": 122839
  },
  "2017-07-19": {
    "open": 24.27,
    "high": 24.5764,
    "low": 22.5,
    "close": 23.07,
    "volume": 210200
  },
  "2017-07-20": {
    "open": 22.81,
    "high": 23.49,
    "low": 21.7,
    "close": 22.77,
    "volume": 150679
  },
  "2017-07-21": {
    "open": 22.95,
    "high": 22.95,
    "low": 21.95,
    "close": 22.75,
    "volume": 138727
  },
  "2017-07-24": {
    "open": 22.43,
    "high": 23.011,
    "low": 21.7,
    "close": 22.27,
    "volume": 155952
  },
  "2017-07-25": {
    "open": 22.1,
    "high": 22.97,
    "low": 20.26,
    "close": 21.33,
    "volume": 196470
  },
  "2017-07-26": {
    "open": 21.26,
    "high": 21.26,
    "low": 20.05,
    "close": 20.05,
    "volume": 254695
  },
  "2017-07-27": {
    "open": 19.84,
    "high": 20.815,
    "low": 19.25,
    "close": 19.87,
    "volume": 249369
  },
  "2017-07-28": {
    "open": 19.77,
    "high": 20.49,
    "low": 19.05,
    "close": 19.5,
    "volume": 274006
  },
  "2017-07-31": {
    "open": 19.41,
    "high": 19.8028,
    "low": 18.1,
    "close": 18.5,
    "volume": 200929
  },
  "2017-08-01": {
    "open": 18.56,
    "high": 19.39,
    "low": 16.98,
    "close": 18.27,
    "volume": 210768
  },
  "2017-08-02": {
    "open": 18.15,
    "high": 18.65,
    "low": 17.1,
    "close": 18.5,
    "volume": 127681
  },
  "2017-08-03": {
    "open": 18.57,
    "high": 20.2,
    "low": 18.57,
    "close": 20.0,
    "volume": 152366
  },
  "2017-08-04": {
    "open": 20.0,
    "high": 20.75,
    "low": 19.5,
    "close": 19.91,
    "volume": 214370
  },
  "2017-08-07": {
    "open": 19.97,
    "high": 20.49,
    "low": 18.13,
    "close": 18.58,
    "volume": 88661
  },
  "2017-08-08": {
    "open": 18.55,
    "high": 19.0,
    "low": 18.08,
    "close": 18.35,
    "volume": 124038
  },
  "2017-08-09": {
    "open": 18.24,
    "high": 20.22,
    "low": 18.2,
    "close": 18.6,
    "volume": 119793
  },
  "2017-08-10": {
    "open": 18.74,
    "high": 18.864,
    "low": 17.55,
    "close": 18.2,
    "volume": 96154
  },
  "2017-08-11": {
    "open": 18.14,
    "high": 18.3928,
    "low": 17.92,
    "close": 18.25,
    "volume": 66362
  },
  "2017-08-14": {
    "open": 18.68,
    "high": 21.81,
    "low": 18.57,
    "close": 21.81,
    "volume": 272165
  },
  "2017-08-15": {
    "open": 21.57,
    "high": 27.18,
    "low": 20.51,
    "close": 26.61,
    "volume": 205218
  },
  "2017-08-16": {
    "open": 26.41,
    "high": 27.5,
    "low": 23.3,
    "close": 26.21,
    "volume": 207003
  },
  "2017-08-17": {
    "open": 24.22,
    "high": 26.2,
    "low": 24.0,
    "close": 25.63,
    "volume": 89562
  },
  "2017-08-18": {
    "open": 26.14,
    "high": 26.82,
    "low": 24.7011,
    "close": 25.8,
    "volume": 86964
  },
  "2017-08-21": {
    "open": 26.25,
    "high": 27.83,
    "low": 25.1975,
    "close": 26.33,
    "volume": 116334
  },
  "2017-08-22": {
    "open": 26.74,
    "high": 27.1894,
    "low": 25.2415,
    "close": 25.72,
    "volume": 96121
  },
  "2017-08-23": {
    "open": 25.61,
    "high": 26.89,
    "low": 25.0375,
    "close": 25.77,
    "volume": 81609
  },
  "2017-08-24": {
    "open": 26.16,
    "high": 26.268,
    "low": 24.75,
    "close": 25.32,
    "volume": 163478
  },
  "2017-08-25": {
    "open": 25.2,
    "high": 26.348,
    "low": 23.5,
    "close": 24.89,
    "volume": 126098
  },
  "2017-08-28": {
    "open": 24.77,
    "high": 25.3,
    "low": 23.9067,
    "close": 24.98,
    "volume": 64138
  },
  "2017-08-29": {
    "open": 25.0,
    "high": 25.94,
    "low": 24.18,
    "close": 24.94,
    "volume": 92579
  },
  "2017-08-30": {
    "open": 25.22,
    "high": 26.0,
    "low": 24.001,
    "close": 24.75,
    "volume": 95004
  },
  "2017-08-31": {
    "open": 24.5,
    "high": 26.0092,
    "low": 24.3468,
    "close": 24.7,
    "volume": 116624
  },
  "2017-09-01": {
    "open": 24.45,
    "high": 25.38,
    "low": 23.2001,
    "close": 24.7,
    "volume": 116740
  },
  "2017-09-05": {
    "open": 25.73,
    "high": 28.2435,
    "low": 23.9169,
    "close": 26.04,
    "volume": 193863
  },
  "2017-09-06": {
    "open": 26.24,
    "high": 26.88,
    "low": 25.3,
    "close": 26.21,
    "volume": 83494
  },
  "2017-09-07": {
    "open": 26.1,
    "high": 27.675,
    "low": 25.72,
    "close": 26.64,
    "volume": 88520
  },
  "2017-09-08": {
    "open": 26.43,
    "high": 27.5,
    "low": 26.41,
    "close": 26.9,
    "volume": 72004
  },
  "2017-09-11": {
    "open": 27.64,
    "high": 27.93,
    "low": 26.17,
    "close": 26.81,
    "volume": 83087
  },
  "2017-09-12": {
    "open": 26.8,
    "high": 27.42,
    "low": 26.41,
    "close": 26.74,
    "volume": 101399
  },
  "2017-09-13": {
    "open": 26.57,
    "high": 27.3724,
    "low": 25.4,
    "close": 26.24,
    "volume": 120003
  },
  "2017-09-14": {
    "open": 26.5,
    "high": 27.47,
    "low": 25.5,
    "close": 26.5,
    "volume": 76339
  },
  "2017-09-15": {
    "open": 26.49,
    "high": 27.55,
    "low": 26.12,
    "close": 26.38,
    "volume": 601529
  },
  "2017-09-18": {
    "open": 26.35,
    "high": 27.1878,
    "low": 24.85,
    "close": 26.16,
    "volume": 107772
  },
  "2017-09-19": {
    "open": 26.35,
    "high": 26.96,
    "low": 25.17,
    "close": 25.83,
    "volume": 117789
  },
  "2017-09-20": {
    "open": 26.5216,
    "high": 26.74,
    "low": 25.01,
    "close": 25.61,
    "volume": 115711
  },
  "2017-09-21": {
    "open": 25.42,
    "high": 26.27,
    "low": 25.1,
    "close": 25.37,
    "volume": 82099
  },
  "2017-09-22": {
    "open": 25.63,
    "high": 26.0,
    "low": 24.0,
    "close": 24.54,
    "volume": 257078
  },
  "2017-09-25": {
    "open": 24.4,
    "high": 25.3002,
    "low": 21.825,
    "close": 22.45,
    "volume": 170860
  },
  "2017-09-26": {
    "open": 23.8,
    "high": 24.45,
    "low": 23.19,
    "close": 24.07,
    "volume": 148280
  },
  "2017-09-27": {
    "open": 24.19,
    "high": 24.78,
    "low": 23.56,
    "close": 24.47,
    "volume": 126695
  },
  "2017-09-28": {
    "open": 24.67,
    "high": 25.0,
    "low": 24.04,
    "close": 24.48,
    "volume": 84634
  },
  "2017-09-29": {
    "open": 24.5,
    "high": 24.8,
    "low": 23.91,
    "close": 24.28,
    "volume": 108929
  },
  "2017-10-02": {
    "open": 24.48,
    "high": 26.0,
    "low": 24.03,
    "close": 25.57,
    "volume": 85256
  },
  "2017-10-03": {
    "open": 25.91,
    "high": 26.0083,
    "low": 25.13,
    "close": 25.48,
    "volume": 92915
  },
  "2017-10-04": {
    "open": 25.68,
    "high": 26.5,
    "low": 25.0003,
    "close": 26.04,
    "volume": 73379
  },
  "2017-10-05": {
    "open": 26.29,
    "high": 26.73,
    "low": 25.8675,
    "close": 26.63,
    "volume": 58816
  },
  "2017-10-06": {
    "open": 26.6,
    "high": 27.93,
    "low": 26.6,
    "close": 27.85,
    "volume": 33214
  },
  "2017-10-09": {
    "open": 27.9869,
    "high": 29.99,
    "low": 27.96,
    "close": 28.27,
    "volume": 81637
  },
  "2017-10-10": {
    "open": 28.0,
    "high": 29.16,
    "low": 27.295,
    "close": 27.63,
    "volume": 102782
  },
  "2017-10-11": {
    "open": 28.06,
    "high": 29.37,
    "low": 27.69,
    "close": 27.81,
    "volume": 83303
  },
  "2017-10-12": {
    "open": 28.27,
    "high": 28.79,
    "low": 27.56,
    "close": 27.99,
    "volume": 31675
  },
  "2017-10-13": {
    "open": 28.17,
    "high": 29.37,
    "low": 28.05,
    "close": 28.46,
    "volume": 78345
  },
  "2017-10-16": {
    "open": 29.0,
    "high": 29.26,
    "low": 28.2286,
    "close": 28.46,
    "volume": 104059
  },
  "2017-10-17": {
    "open": 28.17,
    "high": 28.71,
    "low": 27.51,
    "close": 27.81,
    "volume": 69598
  },
  "2017-10-18": {
    "open": 27.41,
    "high": 28.25,
    "low": 27.0,
    "close": 27.47,
    "volume": 59879
  },
  "2017-10-19": {
    "open": 27.39,
    "high": 27.5,
    "low": 26.17,
    "close": 27.13,
    "volume": 137750
  },
  "2017-10-20": {
    "open": 27.0,
    "high": 27.0,
    "low": 26.32,
    "close": 26.73,
    "volume": 57832
  },
  "2017-10-23": {
    "open": 26.0,
    "high": 27.45,
    "low": 25.91,
    "close": 26.5,
    "volume": 73642
  },
  "2017-10-24": {
    "open": 26.85,
    "high": 26.85,
    "low": 25.17,
    "close": 26.42,
    "volume": 110517
  },
  "2017-10-25": {
    "open": 26.92,
    "high": 26.92,
    "low": 25.0,
    "close": 25.36,
    "volume": 49518
  },
  "2017-10-26": {
    "open": 25.775,
    "high": 26.38,
    "low": 25.32,
    "close": 25.42,
    "volume": 32561
  },
  "2017-10-27": {
    "open": 25.62,
    "high": 25.68,
    "low": 24.45,
    "close": 24.8,
    "volume": 55809
  },
  "2017-10-30": {
    "open": 24.86,
    "high": 26.44,
    "low": 24.72,
    "close": 25.34,
    "volume": 90670
  },
  "2017-10-31": {
    "open": 25.5,
    "high": 25.5,
    "low": 24.78,
    "close": 25.06,
    "volume": 58439
  },
  "2017-11-01": {
    "open": 25.12,
    "high": 25.2,
    "low": 24.01,
    "close": 24.99,
    "volume": 81881
  },
  "2017-11-02": {
    "open": 25.05,
    "high": 25.5,
    "low": 24.59,
    "close": 25.09,
    "volume": 54133
  },
  "2017-11-03": {
    "open": 24.95,
    "high": 25.29,
    "low": 24.26,
    "close": 24.95,
    "volume": 34377
  },
  "2017-11-06": {
    "open": 25.14,
    "high": 25.98,
    "low": 24.93,
    "close": 25.51,
    "volume": 55333
  },
  "2017-11-07": {
    "open": 25.35,
    "high": 25.45,
    "low": 23.97,
    "close": 24.11,
    "volume": 72814
  },
  "2017-11-08": {
    "open": 24.28,
    "high": 24.58,
    "low": 23.11,
    "close": 24.19,
    "volume": 94415
  },
  "2017-11-09": {
    "open": 24.06,
    "high": 24.68,
    "low": 23.53,
    "close": 23.82,
    "volume": 41898
  },
  "2017-11-10": {
    "open": 22.0,
    "high": 24.42,
    "low": 22.0,
    "close": 23.13,
    "volume": 52908
  },
  "2017-11-13": {
    "open": 23.24,
    "high": 25.18,
    "low": 23.24,
    "close": 24.92,
    "volume": 38584
  },
  "2017-11-14": {
    "open": 24.09,
    "high": 24.19,
    "low": 22.24,
    "close": 22.57,
    "volume": 56470
  },
  "2017-11-15": {
    "open": 22.72,
    "high": 24.46,
    "low": 22.72,
    "close": 24.3,
    "volume": 29989
  },
  "2017-11-16": {
    "open": 24.92,
    "high": 27.0,
    "low": 24.3001,
    "close": 26.28,
    "volume": 59079
  },
  "2017-11-17": {
    "open": 26.05,
    "high": 26.75,
    "low": 26.05,
    "close": 26.7,
    "volume": 18989
  },
  "2017-11-20": {
    "open": 26.77,
    "high": 26.77,
    "low": 26.09,
    "close": 26.42,
    "volume": 32430
  },
  "2017-11-21": {
    "open": 26.67,
    "high": 26.79,
    "low": 26.235,
    "close": 26.75,
    "volume": 28072
  },
  "2017-11-22": {
    "open": 26.75,
    "high": 27.95,
    "low": 26.18,
    "close": 27.57,
    "volume": 42929
  },
  "2017-11-24": {
    "open": 27.82,
    "high": 28.83,
    "low": 27.4,
    "close": 28.76,
    "volume": 27460
  },
  "2017-11-27": {
    "open": 28.61,
    "high": 28.96,
    "low": 28.03,
    "close": 28.63,
    "volume": 59697
  },
  "2017-11-28": {
    "open": 29.0,
    "high": 29.0,
    "low": 27.27,
    "close": 27.83,
    "volume": 85974
  },
  "2017-11-29": {
    "open": 28.07,
    "high": 28.72,
    "low": 27.82,
    "close": 28.27,
    "volume": 39353
  },
  "2017-11-30": {
    "open": 28.53,
    "high": 30.48,
    "low": 28.24,
    "close": 29.87,
    "volume": 68600
  },
  "2017-12-01": {
    "open": 29.96,
    "high": 30.3,
    "low": 29.03,
    "close": 30.09,
    "volume": 48505
  },
  "2017-12-04": {
    "open": 30.37,
    "high": 30.37,
    "low": 29.645,
    "close": 29.92,
    "volume": 24448
  },
  "2017-12-05": {
    "open": 30.0,
    "high": 30.0,
    "low": 28.99,
    "close": 29.44,
    "volume": 37615
  },
  "2017-12-06": {
    "open": 29.38,
    "high": 29.65,
    "low": 27.57,
    "close": 29.25,
    "volume": 47885
  },
  "2017-12-07": {
    "open": 29.22,
    "high": 30.92,
    "low": 28.97,
    "close": 29.86,
    "volume": 39525
  },
  "2017-12-08": {
    "open": 30.15,
    "high": 30.15,
    "low": 29.44,
    "close": 29.99,
    "volume": 27974
  },
  "2017-12-11": {
    "open": 30.14,
    "high": 31.67,
    "low": 29.74,
    "close": 30.08,
    "volume": 100653
  },
  "2017-12-12": {
    "open": 30.8,
    "high": 31.27,
    "low": 29.96,
    "close": 30.2,
    "volume": 101794
  },
  "2017-12-13": {
    "open": 30.91,
    "high": 31.87,
    "low": 30.13,
    "close": 31.63,
    "volume": 84706
  },
  "2017-12-14": {
    "open": 31.5,
    "high": 32.75,
    "low": 30.69,
    "close": 32.43,
    "volume": 101181
  },
  "2017-12-15": {
    "open": 32.3,
    "high": 32.46,
    "low": 31.12,
    "close": 31.21,
    "volume": 545634
  },
  "2017-12-18": {
    "open": 32.0,
    "high": 32.5,
    "low": 28.36,
    "close": 29.53,
    "volume": 168758
  },
  "2017-12-19": {
    "open": 29.6,
    "high": 31.14,
    "low": 28.02,
    "close": 28.98,
    "volume": 161795
  },
  "2017-12-20": {
    "open": 29.25,
    "high": 29.25,
    "low": 26.62,
    "close": 28.5,
    "volume": 104165
  },
  "2017-12-21": {
    "open": 28.6,
    "high": 29.91,
    "low": 28.04,
    "close": 29.36,
    "volume": 77918
  },
  "2017-12-22": {
    "open": 28.64,
    "high": 29.21,
    "low": 27.54,
    "close": 28.7,
    "volume": 88770
  },
  "2017-12-26": {
    "open": 28.53,
    "high": 28.86,
    "low": 26.88,
    "close": 28.65,
    "volume": 64915
  },
  "2017-12-27": {
    "open": 28.78,
    "high": 29.4,
    "low": 28.0,
    "close": 28.54,
    "volume": 78960
  },
  "2017-12-28": {
    "open": 28.76,
    "high": 28.97,
    "low": 28.44,
    "close": 28.58,
    "volume": 121554
  },
  "2017-12-29": {
    "open": 28.64,
    "high": 29.71,
    "low": 28.04,
    "close": 28.8,
    "volume": 85231
  },
  "2018-01-02": {
    "open": 28.7,
    "high": 29.0,
    "low": 26.0,
    "close": 27.66,
    "volume": 95638
  },
  "2018-01-03": {
    "open": 27.65,
    "high": 28.01,
    "low": 25.63,
    "close": 26.23,
    "volume": 65386
  },
  "2018-01-04": {
    "open": 27.81,
    "high": 28.1,
    "low": 26.02,
    "close": 26.35,
    "volume": 191629
  },
  "2018-01-05": {
    "open": 26.37,
    "high": 28.74,
    "low": 26.37,
    "close": 28.55,
    "volume": 92875
  },
  "2018-01-08": {
    "open": 28.75,
    "high": 29.35,
    "low": 27.4,
    "close": 29.19,
    "volume": 599996
  },
  "2018-01-09": {
    "open": 29.71,
    "high": 30.325,
    "low": 29.43,
    "close": 30.04,
    "volume": 56460
  },
  "2018-01-10": {
    "open": 29.95,
    "high": 30.2,
    "low": 29.655,
    "close": 30.05,
    "volume": 50075
  },
  "2018-01-11": {
    "open": 29.91,
    "high": 30.45,
    "low": 29.0,
    "close": 29.52,
    "volume": 72791
  },
  "2018-01-12": {
    "open": 29.85,
    "high": 30.38,
    "low": 29.57,
    "close": 29.72,
    "volume": 25223
  },
  "2018-01-16": {
    "open": 30.03,
    "high": 30.5388,
    "low": 27.63,
    "close": 28.7,
    "volume": 47388
  },
  "2018-01-17": {
    "open": 29.41,
    "high": 30.55,
    "low": 29.011,
    "close": 30.22,
    "volume": 124543
  },
  "2018-01-18": {
    "open": 30.29,
    "high": 31.06,
    "low": 29.735,
    "close": 30.55,
    "volume": 115758
  },
  "2018-01-19": {
    "open": 30.89,
    "high": 31.5179,
    "low": 30.4,
    "close": 30.9,
    "volume": 138493
  },
  "2018-01-22": {
    "open": 30.9289,
    "high": 31.4899,
    "low": 30.07,
    "close": 31.0,
    "volume": 58673
  },
  "2018-01-23": {
    "open": 31.14,
    "high": 31.14,
    "low": 29.85,
    "close": 30.2,
    "volume": 67124
  },
  "2018-01-24": {
    "open": 30.08,
    "high": 30.501,
    "low": 29.655,
    "close": 29.83,
    "volume": 75430
  },
  "2018-01-25": {
    "open": 30.06,
    "high": 30.94,
    "low": 29.69,
    "close": 30.08,
    "volume": 59057
  },
  "2018-01-26": {
    "open": 30.83,
    "high": 33.215,
    "low": 30.35,
    "close": 31.85,
    "volume": 169951
  },
  "2018-01-29": {
    "open": 32.23,
    "high": 32.92,
    "low": 31.35,
    "close": 32.29,
    "volume": 45763
  },
  "2018-01-30": {
    "open": 31.74,
    "high": 32.76,
    "low": 31.1378,
    "close": 31.81,
    "volume": 37607
  },
  "2018-01-31": {
    "open": 32.07,
    "high": 32.34,
    "low": 31.23,
    "close": 31.86,
    "volume": 73697
  },
  "2018-02-01": {
    "open": 31.55,
    "high": 32.3,
    "low": 31.31,
    "close": 31.49,
    "volume": 45185
  },
  "2018-02-02": {
    "open": 31.328,
    "high": 31.99,
    "low": 30.74,
    "close": 30.74,
    "volume": 18500
  },
  "2018-02-05": {
    "open": 30.49,
    "high": 31.71,
    "low": 30.0,
    "close": 30.37,
    "volume": 45569
  },
  "2018-02-06": {
    "open": 29.75,
    "high": 30.65,
    "low": 28.62,
    "close": 30.11,
    "volume": 64806
  },
  "2018-02-07": {
    "open": 29.86,
    "high": 30.74,
    "low": 29.86,
    "close": 30.11,
    "volume": 28752
  },
  "2018-02-08": {
    "open": 30.24,
    "high": 31.37,
    "low": 29.27,
    "close": 29.49,
    "volume": 59212
  },
  "2018-02-09": {
    "open": 31.2627,
    "high": 31.2627,
    "low": 29.45,
    "close": 30.58,
    "volume": 91676
  },
  "2018-02-12": {
    "open": 30.0695,
    "high": 31.64,
    "low": 30.0695,
    "close": 30.85,
    "volume": 51553
  },
  "2018-02-13": {
    "open": 30.78,
    "high": 31.48,
    "low": 30.73,
    "close": 31.47,
    "volume": 55265
  },
  "2018-02-14": {
    "open": 31.11,
    "high": 32.0,
    "low": 30.3,
    "close": 31.98,
    "volume": 64441
  },
  "2018-02-15": {
    "open": 32.01,
    "high": 35.0,
    "low": 30.85,
    "close": 33.9,
    "volume": 198465
  },
  "2018-02-16": {
    "open": 34.05,
    "high": 35.0,
    "low": 31.094,
    "close": 34.68,
    "volume": 99394
  },
  "2018-02-20": {
    "open": 34.5,
    "high": 37.0,
    "low": 34.1,
    "close": 34.71,
    "volume": 53904
  },
  "2018-02-21": {
    "open": 34.01,
    "high": 34.01,
    "low": 31.9802,
    "close": 32.86,
    "volume": 108040
  },
  "2018-02-22": {
    "open": 33.48,
    "high": 34.38,
    "low": 32.3,
    "close": 32.78,
    "volume": 129839
  },
  "2018-02-23": {
    "open": 33.0,
    "high": 33.38,
    "low": 31.09,
    "close": 32.31,
    "volume": 1506810
  },
  "2018-02-26": {
    "open": 32.12,
    "high": 32.8607,
    "low": 31.69,
    "close": 32.01,
    "volume": 117905
  },
  "2018-02-27": {
    "open": 31.91,
    "high": 32.02,
    "low": 30.55,
    "close": 31.18,
    "volume": 107319
  },
  "2018-02-28": {
    "open": 31.3,
    "high": 31.44,
    "low": 30.145,
    "close": 30.26,
    "volume": 121094
  },
  "2018-03-01": {
    "open": 30.26,
    "high": 30.9,
    "low": 28.55,
    "close": 29.28,
    "volume": 138190
  },
  "2018-03-02": {
    "open": 29.0,
    "high": 30.0,
    "low": 28.6101,
    "close": 29.51,
    "volume": 135008
  },
  "2018-03-05": {
    "open": 29.3,
    "high": 30.15,
    "low": 29.01,
    "close": 29.55,
    "volume": 80326
  },
  "2018-03-06": {
    "open": 29.57,
    "high": 30.36,
    "low": 28.95,
    "close": 29.31,
    "volume": 50673
  },
  "2018-03-07": {
    "open": 29.18,
    "high": 29.9,
    "low": 29.0099,
    "close": 29.34,
    "volume": 46176
  },
  "2018-03-08": {
    "open": 29.61,
    "high": 29.81,
    "low": 29.0,
    "close": 29.73,
    "volume": 95921
  },
  "2018-03-09": {
    "open": 29.83,
    "high": 30.58,
    "low": 29.22,
    "close": 29.62,
    "volume": 151354
  },
  "2018-03-12": {
    "open": 30.0,
    "high": 30.2,
    "low": 29.16,
    "close": 29.33,
    "volume": 93995
  },
  "2018-03-13": {
    "open": 29.33,
    "high": 30.0801,
    "low": 29.035,
    "close": 29.17,
    "volume": 95044
  },
  "2018-03-14": {
    "open": 29.23,
    "high": 29.7484,
    "low": 28.31,
    "close": 28.73,
    "volume": 96859
  },
  "2018-03-15": {
    "open": 28.7,
    "high": 29.15,
    "low": 27.07,
    "close": 27.35,
    "volume": 136648
  },
  "2018-03-16": {
    "open": 27.39,
    "high": 27.85,
    "low": 27.0,
    "close": 27.18,
    "volume": 238066
  },
  "2018-03-19": {
    "open": 27.2,
    "high": 27.98,
    "low": 24.55,
    "close": 25.0,
    "volume": 192220
  },
  "2018-03-20": {
    "open": 25.0,
    "high": 26.7715,
    "low": 24.38,
    "close": 26.19,
    "volume": 188562
  },
  "2018-03-21": {
    "open": 26.22,
    "high": 28.5,
    "low": 26.08,
    "close": 28.01,
    "volume": 234441
  },
  "2018-03-22": {
    "open": 27.64,
    "high": 31.01,
    "low": 27.64,
    "close": 30.0,
    "volume": 305771
  },
  "2018-03-23": {
    "open": 30.03,
    "high": 31.9,
    "low": 28.76,
    "close": 29.33,
    "volume": 302519
  },
  "2018-03-26": {
    "open": 29.59,
    "high": 30.5137,
    "low": 28.05,
    "close": 28.87,
    "volume": 59857
  },
  "2018-03-27": {
    "open": 28.83,
    "high": 29.04,
    "low": 26.81,
    "close": 27.04,
    "volume": 139485
  },
  "2018-03-28": {
    "open": 27.13,
    "high": 28.77,
    "low": 26.43,
    "close": 26.8,
    "volume": 83622
  },
  "2018-03-29": {
    "open": 26.95,
    "high": 27.715,
    "low": 26.72,
    "close": 27.12,
    "volume": 213246
  },
  "2018-04-02": {
    "open": 27.03,
    "high": 28.49,
    "low": 26.15,
    "close": 26.62,
    "volume": 117391
  },
  "2018-04-03": {
    "open": 26.72,
    "high": 27.5,
    "low": 25.5501,
    "close": 26.68,
    "volume": 104280
  },
  "2018-04-04": {
    "open": 26.27,
    "high": 27.87,
    "low": 26.06,
    "close": 27.56,
    "volume": 113727
  },
  "2018-04-05": {
    "open": 27.81,
    "high": 28.085,
    "low": 27.16,
    "close": 27.48,
    "volume": 131671
  },
  "2018-04-06": {
    "open": 27.51,
    "high": 30.2299,
    "low": 27.51,
    "close": 28.31,
    "volume": 439646
  },
  "2018-04-09": {
    "open": 28.7,
    "high": 29.2499,
    "low": 27.19,
    "close": 27.89,
    "volume": 148861
  },
  "2018-04-10": {
    "open": 28.28,
    "high": 29.19,
    "low": 28.11,
    "close": 28.79,
    "volume": 97423
  },
  "2018-04-11": {
    "open": 28.58,
    "high": 29.2,
    "low": 27.6,
    "close": 28.72,
    "volume": 107039
  },
  "2018-04-12": {
    "open": 28.76,
    "high": 28.76,
    "low": 26.73,
    "close": 27.0,
    "volume": 275163
  },
  "2018-04-13": {
    "open": 27.0,
    "high": 27.29,
    "low": 25.4848,
    "close": 26.17,
    "volume": 138768
  },
  "2018-04-16": {
    "open": 26.03,
    "high": 26.47,
    "low": 25.75,
    "close": 26.17,
    "volume": 47629
  },
  "2018-04-17": {
    "open": 26.0,
    "high": 26.45,
    "low": 25.4,
    "close": 25.59,
    "volume": 74288
  },
  "2018-04-18": {
    "open": 25.71,
    "high": 26.0,
    "low": 25.37,
    "close": 25.64,
    "volume": 42916
  },
  "2018-04-19": {
    "open": 25.58,
    "high": 25.6499,
    "low": 24.29,
    "close": 24.95,
    "volume": 153194
  },
  "2018-04-20": {
    "open": 25.0,
    "high": 25.8456,
    "low": 25.0,
    "close": 25.33,
    "volume": 87230
  },
  "2018-04-23": {
    "open": 25.57,
    "high": 25.9,
    "low": 24.05,
    "close": 24.46,
    "volume": 84928
  },
  "2018-04-24": {
    "open": 24.53,
    "high": 26.31,
    "low": 24.26,
    "close": 25.3,
    "volume": 135732
  },
  "2018-04-25": {
    "open": 25.2,
    "high": 25.99,
    "low": 24.095,
    "close": 24.51,
    "volume": 105144
  },
  "2018-04-26": {
    "open": 26.24,
    "high": 26.24,
    "low": 25.135,
    "close": 25.81,
    "volume": 119642
  },
  "2018-04-27": {
    "open": 25.95,
    "high": 25.95,
    "low": 24.96,
    "close": 25.31,
    "volume": 86706
  },
  "2018-04-30": {
    "open": 25.36,
    "high": 29.42,
    "low": 25.36,
    "close": 28.81,
    "volume": 646445
  },
  "2018-05-01": {
    "open": 28.94,
    "high": 29.0,
    "low": 27.5309,
    "close": 27.95,
    "volume": 181574
  },
  "2018-05-02": {
    "open": 28.0,
    "high": 28.8,
    "low": 28.0,
    "close": 28.09,
    "volume": 161938
  },
  "2018-05-03": {
    "open": 28.35,
    "high": 28.35,
    "low": 27.6,
    "close": 27.8,
    "volume": 156770
  },
  "2018-05-04": {
    "open": 27.61,
    "high": 28.0,
    "low": 26.14,
    "close": 26.22,
    "volume": 177725
  },
  "2018-05-07": {
    "open": 26.35,
    "high": 26.72,
    "low": 25.5623,
    "close": 25.73,
    "volume": 114602
  },
  "2018-05-08": {
    "open": 25.83,
    "high": 26.4,
    "low": 25.5,
    "close": 26.02,
    "volume": 164269
  },
  "2018-05-09": {
    "open": 26.05,
    "high": 26.5,
    "low": 26.0,
    "close": 26.05,
    "volume": 138611
  },
  "2018-05-10": {
    "open": 25.96,
    "high": 26.3,
    "low": 23.0137,
    "close": 23.915,
    "volume": 754059
  },
  "2018-05-11": {
    "open": 24.0,
    "high": 26.27,
    "low": 24.0,
    "close": 25.23,
    "volume": 273185
  },
  "2018-05-14": {
    "open": 26.4,
    "high": 27.195,
    "low": 25.72,
    "close": 26.3,
    "volume": 359574
  },
  "2018-05-15": {
    "open": 26.3,
    "high": 26.81,
    "low": 25.83,
    "close": 26.18,
    "volume": 193674
  },
  "2018-05-16": {
    "open": 26.75,
    "high": 27.28,
    "low": 26.2,
    "close": 27.13,
    "volume": 226221
  },
  "2018-05-17": {
    "open": 27.13,
    "high": 27.32,
    "low": 26.56,
    "close": 26.65,
    "volume": 182081
  },
  "2018-05-18": {
    "open": 26.79,
    "high": 27.94,
    "low": 26.5,
    "close": 27.84,
    "volume": 344211
  },
  "2018-05-21": {
    "open": 27.98,
    "high": 28.79,
    "low": 23.21,
    "close": 24.165,
    "volume": 1857473
  },
  "2018-05-22": {
    "open": 24.61,
    "high": 26.0,
    "low": 24.3,
    "close": 25.82,
    "volume": 511103
  },
  "2018-05-23": {
    "open": 25.61,
    "high": 26.56,
    "low": 24.58,
    "close": 24.94,
    "volume": 432193
  },
  "2018-05-24": {
    "open": 24.83,
    "high": 25.65,
    "low": 24.7,
    "close": 25.0,
    "volume": 134084
  },
  "2018-05-25": {
    "open": 24.99,
    "high": 25.34,
    "low": 24.76,
    "close": 24.86,
    "volume": 113595
  },
  "2018-05-29": {
    "open": 24.86,
    "high": 25.42,
    "low": 23.61,
    "close": 23.73,
    "volume": 196121
  },
  "2018-05-30": {
    "open": 23.73,
    "high": 24.22,
    "low": 21.8024,
    "close": 22.65,
    "volume": 412779
  },
  "2018-05-31": {
    "open": 22.75,
    "high": 22.8,
    "low": 21.86,
    "close": 21.99,
    "volume": 412043
  },
  "2018-06-01": {
    "open": 22.0,
    "high": 23.73,
    "low": 21.05,
    "close": 23.49,
    "volume": 370323
  },
  "2018-06-04": {
    "open": 23.5,
    "high": 25.53,
    "low": 23.26,
    "close": 25.41,
    "volume": 546400
  },
  "2018-06-05": {
    "open": 25.4,
    "high": 27.3,
    "low": 24.87,
    "close": 26.88,
    "volume": 588696
  },
  "2018-06-06": {
    "open": 28.0,
    "high": 29.34,
    "low": 27.7,
    "close": 29.09,
    "volume": 708852
  },
  "2018-06-07": {
    "open": 29.87,
    "high": 29.87,
    "low": 26.78,
    "close": 27.19,
    "volume": 421685
  },
  "2018-06-08": {
    "open": 27.28,
    "high": 29.02,
    "low": 27.28,
    "close": 28.81,
    "volume": 216453
  },
  "2018-06-11": {
    "open": 28.81,
    "high": 30.26,
    "low": 28.58,
    "close": 29.58,
    "volume": 211933
  },
  "2018-06-12": {
    "open": 29.5,
    "high": 29.88,
    "low": 28.69,
    "close": 28.99,
    "volume": 273722
  },
  "2018-06-13": {
    "open": 28.71,
    "high": 29.9,
    "low": 28.595,
    "close": 29.3,
    "volume": 171478
  },
  "2018-06-14": {
    "open": 29.54,
    "high": 30.41,
    "low": 29.4269,
    "close": 30.35,
    "volume": 163868
  },
  "2018-06-15": {
    "open": 30.42,
    "high": 32.62,
    "low": 29.35,
    "close": 30.31,
    "volume": 588663
  },
  "2018-06-18": {
    "open": 30.01,
    "high": 31.155,
    "low": 29.655,
    "close": 30.35,
    "volume": 136746
  },
  "2018-06-19": {
    "open": 30.35,
    "high": 32.0,
    "low": 29.4467,
    "close": 30.11,
    "volume": 162477
  },
  "2018-06-20": {
    "open": 30.14,
    "high": 30.6,
    "low": 28.86,
    "close": 30.35,
    "volume": 223688
  },
  "2018-06-21": {
    "open": 30.23,
    "high": 31.12,
    "low": 29.67,
    "close": 30.07,
    "volume": 150828
  },
  "2018-06-22": {
    "open": 30.18,
    "high": 31.97,
    "low": 30.18,
    "close": 31.85,
    "volume": 881360
  },
  "2018-06-25": {
    "open": 32.03,
    "high": 34.225,
    "low": 31.4137,
    "close": 33.47,
    "volume": 326434
  },
  "2018-06-26": {
    "open": 33.75,
    "high": 35.33,
    "low": 33.02,
    "close": 34.13,
    "volume": 264725
  },
  "2018-06-27": {
    "open": 34.11,
    "high": 34.2923,
    "low": 29.53,
    "close": 30.61,
    "volume": 344043
  },
  "2018-06-28": {
    "open": 30.61,
    "high": 32.05,
    "low": 30.36,
    "close": 31.25,
    "volume": 235430
  },
  "2018-06-29": {
    "open": 31.12,
    "high": 31.63,
    "low": 29.56,
    "close": 29.92,
    "volume": 176142
  },
  "2018-07-02": {
    "open": 29.65,
    "high": 30.02,
    "low": 28.81,
    "close": 29.43,
    "volume": 125587
  },
  "2018-07-03": {
    "open": 29.41,
    "high": 30.3,
    "low": 29.1088,
    "close": 29.81,
    "volume": 44071
  },
  "2018-07-05": {
    "open": 30.07,
    "high": 30.3599,
    "low": 28.98,
    "close": 29.12,
    "volume": 144694
  },
  "2018-07-06": {
    "open": 29.26,
    "high": 29.715,
    "low": 28.62,
    "close": 29.21,
    "volume": 94835
  },
  "2018-07-09": {
    "open": 27.25,
    "high": 27.25,
    "low": 24.12,
    "close": 25.54,
    "volume": 1426107
  },
  "2018-07-10": {
    "open": 24.93,
    "high": 25.38,
    "low": 23.2,
    "close": 23.575,
    "volume": 913646
  },
  "2018-07-11": {
    "open": 23.36,
    "high": 24.12,
    "low": 22.51,
    "close": 22.65,
    "volume": 374382
  },
  "2018-07-12": {
    "open": 22.69,
    "high": 23.74,
    "low": 22.19,
    "close": 22.83,
    "volume": 387825
  },
  "2018-07-13": {
    "open": 23.0,
    "high": 23.4132,
    "low": 22.42,
    "close": 23.3,
    "volume": 239818
  },
  "2018-07-16": {
    "open": 23.2,
    "high": 23.4837,
    "low": 22.25,
    "close": 22.73,
    "volume": 215625
  },
  "2018-07-17": {
    "open": 22.63,
    "high": 24.24,
    "low": 22.5,
    "close": 23.86,
    "volume": 275486
  },
  "2018-07-18": {
    "open": 23.85,
    "high": 23.999,
    "low": 23.16,
    "close": 23.73,
    "volume": 102778
  },
  "2018-07-19": {
    "open": 23.77,
    "high": 24.54,
    "low": 23.24,
    "close": 24.37,
    "volume": 166672
  },
  "2018-07-20": {
    "open": 24.39,
    "high": 24.65,
    "low": 24.0,
    "close": 24.33,
    "volume": 187403
  },
  "2018-07-23": {
    "open": 24.43,
    "high": 25.1262,
    "low": 24.01,
    "close": 24.25,
    "volume": 315513
  },
  "2018-07-24": {
    "open": 24.27,
    "high": 24.45,
    "low": 23.005,
    "close": 23.12,
    "volume": 202661
  },
  "2018-07-25": {
    "open": 22.98,
    "high": 23.82,
    "low": 22.92,
    "close": 23.73,
    "volume": 198645
  },
  "2018-07-26": {
    "open": 23.77,
    "high": 24.17,
    "low": 23.31,
    "close": 23.63,
    "volume": 192363
  },
  "2018-07-27": {
    "open": 23.67,
    "high": 24.02,
    "low": 22.84,
    "close": 23.27,
    "volume": 155790
  },
  "2018-07-30": {
    "open": 23.12,
    "high": 23.135,
    "low": 21.01,
    "close": 21.63,
    "volume": 319702
  },
  "2018-07-31": {
    "open": 21.63,
    "high": 22.885,
    "low": 21.26,
    "close": 21.57,
    "volume": 275841
  },
  "2018-08-01": {
    "open": 21.65,
    "high": 21.99,
    "low": 21.01,
    "close": 21.31,
    "volume": 241733
  },
  "2018-08-02": {
    "open": 21.32,
    "high": 22.32,
    "low": 20.9082,
    "close": 21.7,
    "volume": 186014
  },
  "2018-08-03": {
    "open": 21.65,
    "high": 22.401,
    "low": 21.34,
    "close": 21.9,
    "volume": 145937
  },
  "2018-08-06": {
    "open": 21.87,
    "high": 22.67,
    "low": 21.7,
    "close": 22.23,
    "volume": 177952
  },
  "2018-08-07": {
    "open": 22.24,
    "high": 22.68,
    "low": 21.86,
    "close": 22.29,
    "volume": 115205
  },
  "2018-08-08": {
    "open": 22.28,
    "high": 22.99,
    "low": 22.0,
    "close": 22.87,
    "volume": 108079
  },
  "2018-08-09": {
    "open": 23.15,
    "high": 23.5,
    "low": 22.44,
    "close": 22.56,
    "volume": 209248
  },
  "2018-08-10": {
    "open": 22.28,
    "high": 23.5,
    "low": 20.65,
    "close": 21.49,
    "volume": 220082
  },
  "2018-08-13": {
    "open": 21.69,
    "high": 24.13,
    "low": 21.69,
    "close": 23.21,
    "volume": 261316
  },
  "2018-08-14": {
    "open": 23.06,
    "high": 23.8,
    "low": 22.55,
    "close": 22.74,
    "volume": 139478
  },
  "2018-08-15": {
    "open": 22.75,
    "high": 22.9,
    "low": 21.54,
    "close": 21.72,
    "volume": 117272
  },
  "2018-08-16": {
    "open": 22.71,
    "high": 23.69,
    "low": 22.6,
    "close": 23.0,
    "volume": 356363
  },
  "2018-08-17": {
    "open": 23.01,
    "high": 23.5,
    "low": 22.63,
    "close": 23.44,
    "volume": 170811
  },
  "2018-08-20": {
    "open": 23.57,
    "high": 23.67,
    "low": 22.7,
    "close": 22.97,
    "volume": 73603
  },
  "2018-08-21": {
    "open": 22.86,
    "high": 23.75,
    "low": 22.86,
    "close": 23.12,
    "volume": 158960
  },
  "2018-08-22": {
    "open": 23.12,
    "high": 24.0,
    "low": 23.0,
    "close": 23.97,
    "volume": 146027
  },
  "2018-08-23": {
    "open": 24.04,
    "high": 24.82,
    "low": 23.82,
    "close": 24.42,
    "volume": 210639
  },
  "2018-08-24": {
    "open": 24.52,
    "high": 25.24,
    "low": 24.4019,
    "close": 25.07,
    "volume": 202068
  },
  "2018-08-27": {
    "open": 25.08,
    "high": 25.79,
    "low": 24.962,
    "close": 25.42,
    "volume": 255503
  },
  "2018-08-28": {
    "open": 25.42,
    "high": 25.63,
    "low": 24.31,
    "close": 24.57,
    "volume": 198277
  },
  "2018-08-29": {
    "open": 25.96,
    "high": 26.0,
    "low": 24.81,
    "close": 25.46,
    "volume": 168173
  },
  "2018-08-30": {
    "open": 25.44,
    "high": 26.49,
    "low": 25.12,
    "close": 25.28,
    "volume": 179972
  },
  "2018-08-31": {
    "open": 25.25,
    "high": 25.59,
    "low": 25.06,
    "close": 25.45,
    "volume": 67418
  },
  "2018-09-04": {
    "open": 25.1,
    "high": 25.1,
    "low": 22.87,
    "close": 23.17,
    "volume": 289472
  },
  "2018-09-05": {
    "open": 23.03,
    "high": 24.89,
    "low": 23.03,
    "close": 23.91,
    "volume": 261263
  },
  "2018-09-06": {
    "open": 24.02,
    "high": 24.37,
    "low": 23.135,
    "close": 23.45,
    "volume": 172067
  },
  "2018-09-07": {
    "open": 23.38,
    "high": 23.99,
    "low": 23.08,
    "close": 23.79,
    "volume": 107733
  },
  "2018-09-10": {
    "open": 24.1,
    "high": 24.13,
    "low": 22.94,
    "close": 23.39,
    "volume": 91630
  },
  "2018-09-11": {
    "open": 23.36,
    "high": 24.055,
    "low": 23.18,
    "close": 23.89,
    "volume": 112501
  },
  "2018-09-12": {
    "open": 23.88,
    "high": 24.26,
    "low": 23.5464,
    "close": 23.96,
    "volume": 119486
  },
  "2018-09-13": {
    "open": 24.1,
    "high": 24.59,
    "low": 23.895,
    "close": 24.17,
    "volume": 149154
  },
  "2018-09-14": {
    "open": 24.17,
    "high": 24.5,
    "low": 23.46,
    "close": 24.24,
    "volume": 144920
  },
  "2018-09-17": {
    "open": 24.52,
    "high": 24.98,
    "low": 24.1,
    "close": 24.48,
    "volume": 176461
  },
  "2018-09-18": {
    "open": 24.54,
    "high": 24.9899,
    "low": 24.0,
    "close": 24.74,
    "volume": 151944
  },
  "2018-09-19": {
    "open": 24.71,
    "high": 25.09,
    "low": 24.33,
    "close": 24.62,
    "volume": 78921
  },
  "2018-09-20": {
    "open": 24.77,
    "high": 25.0,
    "low": 24.4,
    "close": 24.63,
    "volume": 105839
  },
  "2018-09-21": {
    "open": 24.72,
    "high": 24.72,
    "low": 23.5,
    "close": 23.95,
    "volume": 225974
  },
  "2018-09-24": {
    "open": 23.88,
    "high": 24.2199,
    "low": 23.51,
    "close": 24.02,
    "volume": 114655
  },
  "2018-09-25": {
    "open": 24.1,
    "high": 24.4,
    "low": 22.93,
    "close": 23.04,
    "volume": 144903
  },
  "2018-09-26": {
    "open": 23.08,
    "high": 23.61,
    "low": 22.15,
    "close": 22.24,
    "volume": 155105
  },
  "2018-09-27": {
    "open": 22.41,
    "high": 24.23,
    "low": 21.74,
    "close": 21.84,
    "volume": 182085
  },
  "2018-09-28": {
    "open": 22.0,
    "high": 22.01,
    "low": 20.4,
    "close": 20.97,
    "volume": 519938
  },
  "2018-10-01": {
    "open": 21.02,
    "high": 21.64,
    "low": 20.69,
    "close": 20.83,
    "volume": 490619
  },
  "2018-10-02": {
    "open": 20.62,
    "high": 20.75,
    "low": 19.8,
    "close": 20.45,
    "volume": 378363
  },
  "2018-10-03": {
    "open": 20.56,
    "high": 21.13,
    "low": 20.0,
    "close": 21.0,
    "volume": 246630
  },
  "2018-10-04": {
    "open": 20.88,
    "high": 21.22,
    "low": 20.35,
    "close": 20.48,
    "volume": 252461
  },
  "2018-10-05": {
    "open": 20.54,
    "high": 20.71,
    "low": 19.75,
    "close": 20.38,
    "volume": 262269
  },
  "2018-10-08": {
    "open": 20.41,
    "high": 20.84,
    "low": 20.04,
    "close": 20.42,
    "volume": 133210
  },
  "2018-10-09": {
    "open": 20.43,
    "high": 20.8,
    "low": 20.02,
    "close": 20.07,
    "volume": 163182
  },
  "2018-10-10": {
    "open": 20.07,
    "high": 20.6,
    "low": 19.52,
    "close": 20.0,
    "volume": 257889
  },
  "2018-10-11": {
    "open": 19.94,
    "high": 20.59,
    "low": 19.72,
    "close": 19.82,
    "volume": 103572
  },
  "2018-10-12": {
    "open": 20.09,
    "high": 20.98,
    "low": 19.85,
    "close": 20.27,
    "volume": 127346
  },
  "2018-10-15": {
    "open": 20.33,
    "high": 20.44,
    "low": 19.25,
    "close": 19.42,
    "volume": 134770
  },
  "2018-10-16": {
    "open": 19.51,
    "high": 21.26,
    "low": 19.51,
    "close": 21.18,
    "volume": 205267
  },
  "2018-10-17": {
    "open": 20.83,
    "high": 21.24,
    "low": 20.14,
    "close": 20.81,
    "volume": 37419
  },
  "2018-10-18": {
    "open": 20.78,
    "high": 21.5,
    "low": 20.48,
    "close": 20.81,
    "volume": 137259
  },
  "2018-10-19": {
    "open": 20.82,
    "high": 21.34,
    "low": 20.61,
    "close": 20.63,
    "volume": 102685
  },
  "2018-10-22": {
    "open": 20.61,
    "high": 21.0,
    "low": 20.08,
    "close": 20.19,
    "volume": 117993
  },
  "2018-10-23": {
    "open": 19.87,
    "high": 20.55,
    "low": 19.75,
    "close": 20.05,
    "volume": 94241
  },
  "2018-10-24": {
    "open": 20.02,
    "high": 20.475,
    "low": 18.83,
    "close": 18.89,
    "volume": 146344
  },
  "2018-10-25": {
    "open": 19.03,
    "high": 20.54,
    "low": 18.6101,
    "close": 19.88,
    "volume": 315698
  },
  "2018-10-26": {
    "open": 19.52,
    "high": 20.0,
    "low": 19.01,
    "close": 19.44,
    "volume": 180089
  },
  "2018-10-29": {
    "open": 19.49,
    "high": 20.08,
    "low": 18.72,
    "close": 19.0,
    "volume": 98540
  },
  "2018-10-30": {
    "open": 18.96,
    "high": 19.22,
    "low": 18.38,
    "close": 18.57,
    "volume": 74012
  },
  "2018-10-31": {
    "open": 18.82,
    "high": 19.52,
    "low": 18.47,
    "close": 18.56,
    "volume": 90730
  },
  "2018-11-01": {
    "open": 18.71,
    "high": 19.0,
    "low": 18.56,
    "close": 18.9,
    "volume": 95768
  },
  "2018-11-02": {
    "open": 19.04,
    "high": 19.4526,
    "low": 18.64,
    "close": 18.94,
    "volume": 144795
  },
  "2018-11-05": {
    "open": 19.67,
    "high": 20.05,
    "low": 18.17,
    "close": 18.41,
    "volume": 174078
  },
  "2018-11-06": {
    "open": 18.34,
    "high": 19.22,
    "low": 17.73,
    "close": 18.8,
    "volume": 264075
  },
  "2018-11-07": {
    "open": 18.93,
    "high": 19.3,
    "low": 18.18,
    "close": 18.71,
    "volume": 243497
  },
  "2018-11-08": {
    "open": 18.71,
    "high": 19.34,
    "low": 18.29,
    "close": 19.3,
    "volume": 286983
  },
  "2018-11-09": {
    "open": 18.49,
    "high": 18.79,
    "low": 16.6307,
    "close": 16.89,
    "volume": 647924
  },
  "2018-11-12": {
    "open": 17.05,
    "high": 17.21,
    "low": 15.6,
    "close": 16.55,
    "volume": 325618
  },
  "2018-11-13": {
    "open": 16.55,
    "high": 16.99,
    "low": 16.19,
    "close": 16.55,
    "volume": 157931
  },
  "2018-11-14": {
    "open": 16.62,
    "high": 16.82,
    "low": 14.09,
    "close": 14.12,
    "volume": 296632
  },
  "2018-11-15": {
    "open": 14.37,
    "high": 15.69,
    "low": 14.37,
    "close": 15.39,
    "volume": 199713
  },
  "2018-11-16": {
    "open": 15.49,
    "high": 15.89,
    "low": 15.1543,
    "close": 15.5,
    "volume": 162087
  },
  "2018-11-19": {
    "open": 15.38,
    "high": 15.79,
    "low": 14.545,
    "close": 14.98,
    "volume": 154080
  },
  "2018-11-20": {
    "open": 14.96,
    "high": 15.5,
    "low": 14.4993,
    "close": 14.83,
    "volume": 147394
  },
  "2018-11-21": {
    "open": 15.07,
    "high": 15.6684,
    "low": 14.76,
    "close": 15.01,
    "volume": 84029
  },
  "2018-11-23": {
    "open": 15.09,
    "high": 15.77,
    "low": 15.09,
    "close": 15.37,
    "volume": 86238
  },
  "2018-11-26": {
    "open": 15.53,
    "high": 15.78,
    "low": 14.75,
    "close": 15.08,
    "volume": 113558
  },
  "2018-11-27": {
    "open": 15.34,
    "high": 15.39,
    "low": 14.9,
    "close": 15.15,
    "volume": 132971
  },
  "2018-11-28": {
    "open": 15.18,
    "high": 15.33,
    "low": 15.01,
    "close": 15.3,
    "volume": 138052
  },
  "2018-11-29": {
    "open": 15.17,
    "high": 15.25,
    "low": 14.87,
    "close": 14.89,
    "volume": 105098
  },
  "2018-11-30": {
    "open": 14.7,
    "high": 15.09,
    "low": 14.61,
    "close": 14.9,
    "volume": 104977
  },
  "2018-12-03": {
    "open": 15.09,
    "high": 15.41,
    "low": 14.55,
    "close": 15.08,
    "volume": 291400
  },
  "2018-12-04": {
    "open": 15.1,
    "high": 15.41,
    "low": 14.55,
    "close": 14.71,
    "volume": 160276
  },
  "2018-12-06": {
    "open": 14.4,
    "high": 14.86,
    "low": 14.35,
    "close": 14.42,
    "volume": 212277
  },
  "2018-12-07": {
    "open": 14.34,
    "high": 14.7,
    "low": 14.24,
    "close": 14.48,
    "volume": 151293
  },
  "2018-12-10": {
    "open": 14.5,
    "high": 15.54,
    "low": 14.395,
    "close": 15.44,
    "volume": 240771
  },
  "2018-12-11": {
    "open": 15.54,
    "high": 16.03,
    "low": 15.1,
    "close": 15.47,
    "volume": 246913
  },
  "2018-12-12": {
    "open": 15.64,
    "high": 16.22,
    "low": 15.135,
    "close": 15.72,
    "volume": 201974
  },
  "2018-12-13": {
    "open": 15.75,
    "high": 15.75,
    "low": 14.86,
    "close": 14.89,
    "volume": 157683
  },
  "2018-12-14": {
    "open": 14.72,
    "high": 15.31,
    "low": 14.544,
    "close": 14.81,
    "volume": 154525
  },
  "2018-12-17": {
    "open": 14.63,
    "high": 14.63,
    "low": 8.915,
    "close": 9.01,
    "volume": 2221808
  },
  "2018-12-18": {
    "open": 9.06,
    "high": 9.46,
    "low": 6.455,
    "close": 6.88,
    "volume": 1614778
  },
  "2018-12-19": {
    "open": 7.16,
    "high": 7.18,
    "low": 5.93,
    "close": 6.07,
    "volume": 1339605
  },
  "2018-12-20": {
    "open": 6.2,
    "high": 6.73,
    "low": 5.62,
    "close": 5.73,
    "volume": 1181910
  },
  "2018-12-21": {
    "open": 6.2,
    "high": 7.41,
    "low": 6.04,
    "close": 6.8,
    "volume": 1356564
  },
  "2018-12-24": {
    "open": 6.91,
    "high": 8.14,
    "low": 6.88,
    "close": 7.84,
    "volume": 478870
  },
  "2018-12-26": {
    "open": 8.11,
    "high": 8.94,
    "low": 7.48,
    "close": 8.29,
    "volume": 491688
  },
  "2018-12-27": {
    "open": 8.07,
    "high": 8.37,
    "low": 7.78,
    "close": 8.31,
    "volume": 379295
  },
  "2018-12-28": {
    "open": 8.32,
    "high": 8.55,
    "low": 7.91,
    "close": 8.11,
    "volume": 296017
  },
  "2018-12-31": {
    "open": 8.11,
    "high": 8.2995,
    "low": 7.28,
    "close": 7.58,
    "volume": 428277
  },
  "2019-01-02": {
    "open": 7.36,
    "high": 8.79,
    "low": 7.2201,
    "close": 8.74,
    "volume": 194953
  },
  "2019-01-03": {
    "open": 8.45,
    "high": 8.97,
    "low": 8.39,
    "close": 8.46,
    "volume": 282444
  },
  "2019-01-04": {
    "open": 8.62,
    "high": 8.99,
    "low": 8.54,
    "close": 8.82,
    "volume": 246128
  },
  "2019-01-07": {
    "open": 9.14,
    "high": 9.2,
    "low": 8.32,
    "close": 8.79,
    "volume": 346380
  },
  "2019-01-08": {
    "open": 8.84,
    "high": 8.95,
    "low": 7.89,
    "close": 7.9,
    "volume": 280132
  },
  "2019-01-09": {
    "open": 7.99,
    "high": 8.44,
    "low": 7.65,
    "close": 8.29,
    "volume": 224161
  },
  "2019-01-10": {
    "open": 8.23,
    "high": 8.4124,
    "low": 7.56,
    "close": 8.06,
    "volume": 212336
  },
  "2019-01-11": {
    "open": 7.96,
    "high": 8.2975,
    "low": 7.75,
    "close": 8.0,
    "volume": 204930
  },
  "2019-01-14": {
    "open": 8.0,
    "high": 8.01,
    "low": 7.5,
    "close": 7.54,
    "volume": 153447
  }
}